./.gitignore
./PKG-INFO
./README.md
./add_todo_screen.py
./api_client.py
./cli.py
./config.py
./main.py
./pyproject.toml
./test_pydantic.py
./todo_list.py
./uv.lock
terminal_second_brain-0.0.1.dist-info/METADATA
terminal_second_brain-0.0.1.dist-info/WHEEL
terminal_second_brain-0.0.1.dist-info/entry_points.txt
terminal_second_brain-0.0.1.dist-info/RECORD
