Metadata-Version: 2.4
Name: terminal-second-brain
Version: 0.0.1
Summary: Terminal User Interface for Second Brain Todo Application
Project-URL: Homepage, https://github.com/namanvashistha/terminal-second-brain
Project-URL: Repository, https://github.com/namanvashistha/terminal-second-brain
Project-URL: Issues, https://github.com/namanvashistha/terminal-second-brain/issues
Author-email: Naman Vashistha <naman@example.com>
Keywords: notes,productivity,terminal,todo,tui
Classifier: Development Status :: 4 - Beta
Classifier: Environment :: Console
Classifier: Intended Audience :: End Users/Desktop
Classifier: License :: OSI Approved :: MIT License
Classifier: Operating System :: OS Independent
Classifier: Programming Language :: Python :: 3
Classifier: Programming Language :: Python :: 3.13
Classifier: Topic :: Office/Business
Classifier: Topic :: Utilities
Requires-Python: <3.14,>=3.8
Requires-Dist: httpx<0.29.0,>=0.28.0
Requires-Dist: pydantic<2.13.0,==2.12.0
Requires-Dist: rich<14.3.0,>=14.2.0
Requires-Dist: textual<6.3.0,>=6.2.1
